geometry_calculator/__init__.py
geometry_calculator/py.typed
geometry_calculator/shapes.py
geometry_calculator-0.1.0.dist-info/licenses/LICENSE
geometry_calculator-0.1.0.dist-info/METADATA
geometry_calculator-0.1.0.dist-info/WHEEL
geometry_calculator-0.1.0.dist-info/top_level.txt
geometry_calculator-0.1.0.dist-info/RECORD
