Metadata-Version: 2.4
Name: geometry-calculator
Version: 0.1.0
Summary: Advanced geometry calculations library
Author-email: Your Name <your@email.com>
Project-URL: Homepage, https://github.com/TemplarD/geometry-calculator
Project-URL: Documentation, https://github.com/TemplarD/geometry-calculator#readme
Project-URL: Repository, https://github.com/TemplarD/geometry-calculator
Project-URL: Changelog, https://github.com/TemplarD/geometry-calculator/releases
Classifier: Development Status :: 4 - Beta
Classifier: Intended Audience :: Developers
Classifier: Intended Audience :: Education
Classifier: Intended Audience :: Science/Research
Classifier: License :: OSI Approved :: MIT License
Classifier: Programming Language :: Python :: 3
Classifier: Topic :: Scientific/Engineering :: Mathematics
Classifier: Typing :: Typed
Requires-Python: >=3.7
License-File: LICENSE
Provides-Extra: dev
Requires-Dist: pytest>=6.0; extra == "dev"
Requires-Dist: pytest-cov>=2.0; extra == "dev"
Requires-Dist: mypy>=0.910; extra == "dev"
Requires-Dist: flake8>=3.9; extra == "dev"
Requires-Dist: pdoc3>=0.10; extra == "dev"
Dynamic: license-file
